Workbook

Sheet Cover
B2: THANGAMAYIL JEWELLERY LIMITED
B3: Buy-Side Equity DCF Valuation
B5: NSE Ticker | C5: THANGAMAYL
B6: BSE Code | C6: 533158
B7: Sector | C7: Consumer Durables — Jewellery Retail
B8: Valuation date | C8: 25-Jun-2026
B9: Methodology | C9: FCFF, 10-yr explicit + GGM terminal
B10: Current Market Price | C10: =DCF!D83
B12: SCENARIO SUMMARY
C13: Bear | D13: Base | E13: Bull
B14: WACC | C14: =DCF!C74 | D14: =DCF!D74 | E14: =DCF!E74
B15: Terminal growth (g) | C15: =DCF!C73 | D15: =DCF!D73 | E15: =DCF!E73
B16: Enterprise Value (₹ Cr) | C16: =DCF!C78 | D16: =DCF!D78 | E16: =DCF!E78
B17: Equity Value (₹ Cr) | C17: =DCF!C80 | D17: =DCF!D80 | E17: =DCF!E80
B18: Implied value / share (₹) | C18: =DCF!C82 | D18: =DCF!D82 | E18: =DCF!E82
B19: Upside / (Downside) % | C19: =DCF!C84 | D19: =DCF!D84 | E19: =DCF!E84
B21: KEY OBSERVATIONS
B22: • FY26 revenue (₹8,514 Cr, +73% YoY) was amplified by record gold prices; forecasts normalise growth toward terminal rates.
B23: • The stock rose ~200% in 12 months and trades at ~49x earnings; the exchange sought a price-movement clarification in Jun-2026.
B24: • Jewellery is structurally low-margin (EBITDA ~7%) and working-capital heavy (gold ~142 inventory-days), so FCFF conversion is modest.
B25: • Company is in NET DEBT (~₹789 Cr), which reduces equity value below EV.
B26: • All three DCF scenarios imply intrinsic value well below CMP; the reverse DCF shows the market is pricing FCFF far above the explicit model.
B27: • Inputs are sourced from public filings/aggregators; FY26 cash balance and beta are flagged [ESTIMATED]. Tune blue cells on Assumptions to test views.
B29: COLOUR LEGEND
B30: Blue font | C30: Hardcoded input (Assumptions sheet only)
B31: Black font | C31: Formula referencing the same sheet
B32: Green font | C32: Cross-sheet link
B33: Yellow fill | C33: Key output cell
B34: Negatives shown in (parentheses); zeros shown as “–”.
B36: SOURCES & FLAGS
B37: • Financials: screener.in / ETMoney / Rediff Money (standalone, FY25 & FY26, ₹ Cr).
B38: • FY2025 Annual Report is the latest filed on BSE; FY26 figures from announced results.
B39: • Rf: India 10-yr G-Sec 6.77% (TradingEconomics, 25-Jun-2026).
B40: • ERP: Damodaran India total ERP 8.49% (Jan-2026 update).
B41: • Beta: [ESTIMATED] — Yahoo 5Y-monthly 0.98 used as proxy for 2-yr weekly vs Nifty.
B42: • FY26 Cash ₹124 Cr: [ESTIMATED] — FY25 close ₹88.6 Cr + FY26 net cash flow +₹36 Cr.
B43: • CMP ₹5,594: NSE/BSE close 25-Jun-2026.

Sheet Assumptions
A1: THANGAMAYIL JEWELLERY LTD — DCF ASSUMPTIONS
A2: NSE: THANGAMAYL | BSE: 533158 | Sector: Consumer Durables – Jewellery Retail | All figures ₹ Crore unless stated | Currency: INR
A4: A. MARKET & COMPANY DATA (Actuals)
B5: Value | F5: Rationale / Source
A6: Valuation date | B6: 25-Jun-2026 | F6: Last NSE/BSE close used as CMP reference.
A7: Current Market Price (₹/share) | B7: 5594 | F7: Close 25-Jun-2026 (screener.in / ETMoney). 52-wk range ₹1,750–5,765.
A8: Diluted shares outstanding (Cr) | B8: 3.108 | F8: Equity capital ₹31.08 Cr @ FV ₹10 = 3.108 Cr shares (screener.in).
A9: FY26 Revenue (Actual) | B9: 8514 | F9: FY26 (yr-end Mar-2026) standalone net sales (screener.in / ETMoney).
A10: FY25 Revenue (Actual) | B10: 4911 | F10: FY25 standalone net sales (screener.in).
A11: FY26 EBITDA (Actual) | B11: 579 | F11: FY26 operating profit = sales − operating expenses (screener.in). OPM 6.8%.
A12: FY25 EBITDA (Actual) | B12: 219 | F12: FY25 operating profit (screener.in). OPM 4.5%.
A13: FY26 D&A (Actual) | B13: 40 | F13: FY26 depreciation & amortisation (screener.in). ~0.5% of sales.
A14: Total Debt – FY26 (Actual) | B14: 913 | F14: FY26 total borrowings (screener.in). D/E 0.64 (matches AngelOne).
A15: Cash & Equivalents – FY26 | B15: 124 | F15: [ESTIMATED — basis: FY25 close ₹88.6 Cr (Rediff CF) + FY26 net cash flow +₹36 Cr]. FY26 balance-sheet not yet filed; FY25 AR is latest on BSE.
A16: Net Cash (= Cash − Total Debt) | B16: =B15-B14 | F16: Negative ⇒ company is in NET DEBT; reduces equity value.
A18: B. WACC BUILD (market-value weighted, CAPM)
A19: Driver | C19: Bear | D19: Base | E19: Bull | F19: Rationale / Source
A20: Risk-free rate (Rf) | C20: 0.068 | D20: 0.068 | E20: 0.068 | F20: India 10-yr G-Sec yield 6.77% on 25-Jun-2026 (TradingEconomics); benchmark 6.94% 2036 ~6.84%.
A21: Equity risk premium (ERP) | C21: 0.0849 | D21: 0.0849 | E21: 0.0849 | F21: Damodaran India TOTAL ERP, Jan-2026 update (mature 4.74% + India CRP 3.75%).
A22: Beta (levered) | C22: 1.1 | D22: 1 | E22: 0.9 | F22: [ESTIMATED — basis: Yahoo 5Y-monthly β 0.98]. 2-yr weekly vs Nifty not directly sourceable; scenario-flexed ±0.10 for cyclicality of gold demand.
A23: Cost of equity (Ke = Rf+β·ERP) | C23: =C20+C22*C21 | D23: =D20+D22*D21 | E23: =E20+E22*E21 | F23: CAPM. Black = same-sheet formula.
A24: Pre-tax cost of debt (Kd) | C24: 0.08 | D24: 0.08 | E24: 0.08 | F24: FY26 interest ₹68 Cr / avg debt ₹855 Cr = 7.95% (screener.in).
A25: Tax rate | C25: 0.25 | D25: 0.25 | E25: 0.25 | F25: Effective tax FY26 25% / FY25 26% (screener.in); India concessional regime ~25.17%.
A26: After-tax Kd = Kd·(1−tax) | C26: =C24*(1-C25) | D26: =D24*(1-D25) | E26: =E24*(1-E25) | F26: Same-sheet formula.
A27: Weight of equity (We) | C27: 0.95 | D27: 0.95 | E27: 0.95 | F27: Market value: equity = mkt-cap ₹17,388 Cr; debt ₹913 Cr ⇒ We 95.0%.
A28: Weight of debt (Wd) | C28: 0.05 | D28: 0.05 | E28: 0.05 | F28: Debt ₹913 Cr / (17,388+913) = 5.0%.
A29: WACC = We·Ke + Wd·Kd(at) | C29: =C27*C23+C28*C26 | D29: =D27*D23+D28*D26 | E29: =E27*E23+E28*E26 | F29: Linked into DCF discounting.
A31: C. OPERATING ASSUMPTIONS (per scenario)
A32: Driver | C32: Bear | D32: Base | E32: Bull | F32: Rationale / Source
A33: D&A (% of revenue) | C33: 0.005 | D33: 0.005 | E33: 0.005 | F33: FY26 D&A ₹40 Cr = 0.47% of sales; asset-light retail format.
A34: Capex (% of revenue) | C34: 0.012 | D34: 0.018 | E34: 0.022 | F34: FY26 capex ~₹132 Cr = 1.55% of sales. Bull = faster showroom roll-out.
A35: ΔNWC (% of Δrevenue) | C35: 0.13 | D35: 0.11 | E35: 0.09 | F35: Inventory-heavy (gold ~142 inv-days). Incremental NWC ~11% of incremental sales; Bear assumes worse gold tie-up.
A36: Terminal growth (g) | C36: 0.04 | D36: 0.055 | E36: 0.065 | F36: Below India nominal GDP ~10–11%; kept << WACC. Steady-state store + price growth.
A38: D. REVENUE GROWTH % BY YEAR (FY27–FY36)
A39: Scenario | C39: FY27 | D39: FY28 | E39: FY29 | F39: FY30 | G39: FY31 | H39: FY32 | I39: FY33 | J39: FY34 | K39: FY35 | L39: FY36 | N39: FY26 base inflated by record gold prices (+73% YoY). Growth decays toward terminal. 10-yr median historical sales growth ~19%.
A40: Bear | C40: 0.08 | D40: 0.07 | E40: 0.06 | F40: 0.06 | G40: 0.05 | H40: 0.05 | I40: 0.05 | J40: 0.05 | K40: 0.05 | L40: 0.05
A41: Base | C41: 0.15 | D41: 0.14 | E41: 0.13 | F41: 0.12 | G41: 0.11 | H41: 0.1 | I41: 0.09 | J41: 0.085 | K41: 0.08 | L41: 0.075
A42: Bull | C42: 0.22 | D42: 0.2 | E42: 0.18 | F42: 0.16 | G42: 0.14 | H42: 0.13 | I42: 0.12 | J42: 0.11 | K42: 0.1 | L42: 0.09
A44: E. EBITDA MARGIN % BY YEAR (FY27–FY36)
A45: Scenario | C45: FY27 | D45: FY28 | E45: FY29 | F45: FY30 | G45: FY31 | H45: FY32 | I45: FY33 | J45: FY34 | K45: FY35 | L45: FY36 | N45: FY26 OPM 6.8% (FY25 4.5%). Base: mild expansion from scale & studded mix; Bull: premiumisation; Bear: gold volatility & competition.
A46: Bear | C46: 0.062 | D46: 0.06 | E46: 0.059 | F46: 0.058 | G46: 0.057 | H46: 0.057 | I46: 0.056 | J46: 0.056 | K46: 0.055 | L46: 0.055
A47: Base | C47: 0.069 | D47: 0.0695 | E47: 0.07 | F47: 0.0705 | G47: 0.071 | H47: 0.071 | I47: 0.0715 | J47: 0.0715 | K47: 0.072 | L47: 0.072
A48: Bull | C48: 0.072 | D48: 0.075 | E48: 0.077 | F48: 0.079 | G48: 0.08 | H48: 0.081 | I48: 0.082 | J48: 0.083 | K48: 0.084 | L48: 0.085
A50: Flags: [ESTIMATED] inputs — FY26 cash balance (BS not yet filed) and Beta (2-yr weekly proxy). All other inputs sourced from public filings/aggregators.

Sheet DCF
A1: THANGAMAYIL JEWELLERY LTD — DISCOUNTED CASH FLOW (FCFF)
A2: ₹ Crore | 10-yr explicit (FY27–FY36) + Gordon Growth terminal value | Bear / Base / Bull | GREEN = link to Assumptions, BLACK = same-sheet formula
C4: FY26A | D4: FY27E | E4: FY28E | F4: FY29E | G4: FY30E | H4: FY31E | I4: FY32E | J4: FY33E | K4: FY34E | L4: FY35E | M4: FY36E
A5: Discount period (t) | C5: 0 | D5: 1 | E5: 2 | F5: 3 | G5: 4 | H5: 5 | I5: 6 | J5: 7 | K5: 8 | L5: 9 | M5: 10
A7: ① REVENUE BUILD
A8: Revenue growth % | B8: Bear | D8: =Assumptions!C40 | E8: =Assumptions!D40 | F8: =Assumptions!E40 | G8: =Assumptions!F40 | H8: =Assumptions!G40 | I8: =Assumptions!H40 | J8: =Assumptions!I40 | K8: =Assumptions!J40 | ... M8: =Assumptions!L40 | P8: Growth links from Assumptions §D (blue). Revenue compounds off FY26A base.
B9: Base | D9: =Assumptions!C41 | E9: =Assumptions!D41 | F9: =Assumptions!E41 | G9: =Assumptions!F41 | H9: =Assumptions!G41 | I9: =Assumptions!H41 | J9: =Assumptions!I41 | K9: =Assumptions!J41 | ... M9: =Assumptions!L41
B10: Bull | D10: =Assumptions!C42 | E10: =Assumptions!D42 | F10: =Assumptions!E42 | G10: =Assumptions!F42 | H10: =Assumptions!G42 | I10: =Assumptions!H42 | J10: =Assumptions!I42 | K10: =Assumptions!J42 | ... M10: =Assumptions!L42
A11: Revenue (₹ Cr) | B11: Bear | C11: =Assumptions!B9 | D11: =C11*(1+D8) | E11: =D11*(1+E8) | F11: =E11*(1+F8) | G11: =F11*(1+G8) | H11: =G11*(1+H8) | I11: =H11*(1+I8) | J11: =I11*(1+J8) | K11: =J11*(1+K8) | ... M11: =L11*(1+M8)
B12: Base | C12: =Assumptions!B9 | D12: =C12*(1+D9) | E12: =D12*(1+E9) | F12: =E12*(1+F9) | G12: =F12*(1+G9) | H12: =G12*(1+H9) | I12: =H12*(1+I9) | J12: =I12*(1+J9) | K12: =J12*(1+K9) | ... M12: =L12*(1+M9)
B13: Bull | C13: =Assumptions!B9 | D13: =C13*(1+D10) | E13: =D13*(1+E10) | F13: =E13*(1+F10) | G13: =F13*(1+G10) | H13: =G13*(1+H10) | I13: =H13*(1+I10) | J13: =I13*(1+J10) | K13: =J13*(1+K10) | ... M13: =L13*(1+M10)
A15: ② EBITDA BRIDGE
A16: EBITDA margin % | B16: Bear | C16: =Assumptions!B11/Assumptions!B9 | D16: =Assumptions!C46 | E16: =Assumptions!D46 | F16: =Assumptions!E46 | G16: =Assumptions!F46 | H16: =Assumptions!G46 | I16: =Assumptions!H46 | J16: =Assumptions!I46 | K16: =Assumptions!J46 | ... M16: =Assumptions!L46 | P16: Margin links from Assumptions §E. EBITDA = margin × revenue.
B17: Base | C17: =Assumptions!B11/Assumptions!B9 | D17: =Assumptions!C47 | E17: =Assumptions!D47 | F17: =Assumptions!E47 | G17: =Assumptions!F47 | H17: =Assumptions!G47 | I17: =Assumptions!H47 | J17: =Assumptions!I47 | K17: =Assumptions!J47 | ... M17: =Assumptions!L47
B18: Bull | C18: =Assumptions!B11/Assumptions!B9 | D18: =Assumptions!C48 | E18: =Assumptions!D48 | F18: =Assumptions!E48 | G18: =Assumptions!F48 | H18: =Assumptions!G48 | I18: =Assumptions!H48 | J18: =Assumptions!I48 | K18: =Assumptions!J48 | ... M18: =Assumptions!L48
A19: EBITDA (₹ Cr) | B19: Bear | C19: =Assumptions!B11 | D19: =D11*D16 | E19: =E11*E16 | F19: =F11*F16 | G19: =G11*G16 | H19: =H11*H16 | I19: =I11*I16 | J19: =J11*J16 | K19: =K11*K16 | ... M19: =M11*M16
B20: Base | C20: =Assumptions!B11 | D20: =D12*D17 | E20: =E12*E17 | F20: =F12*F17 | G20: =G12*G17 | H20: =H12*H17 | I20: =I12*I17 | J20: =J12*J17 | K20: =K12*K17 | ... M20: =M12*M17
B21: Bull | C21: =Assumptions!B11 | D21: =D13*D18 | E21: =E13*E18 | F21: =F13*F18 | G21: =G13*G18 | H21: =H13*H18 | I21: =I13*I18 | J21: =J13*J18 | K21: =K13*K18 | ... M21: =M13*M18
A23: ③ FCFF WATERFALL (EBITDA → D&A → EBIT → Tax → NOPAT → +D&A → −Capex → −ΔNWC → FCFF)
C24: FY26A | D24: FY27E | E24: FY28E | F24: FY29E | G24: FY30E | H24: FY31E | I24: FY32E | J24: FY33E | K24: FY34E | L24: FY35E | M24: FY36E
A25: EBITDA | B25: Bear | D25: =D19 | E25: =E19 | F25: =F19 | G25: =G19 | H25: =H19 | I25: =I19 | J25: =J19 | K25: =K19 | ... M25: =M19
B26: Base | D26: =D20 | E26: =E20 | F26: =F20 | G26: =G20 | H26: =H20 | I26: =I20 | J26: =J20 | K26: =K20 | ... M26: =M20
B27: Bull | D27: =D21 | E27: =E21 | F27: =F21 | G27: =G21 | H27: =H21 | I27: =I21 | J27: =J21 | K27: =K21 | ... M27: =M21
A28: (−) D&A | B28: Bear | D28: =-D11*Assumptions!C33 | E28: =-E11*Assumptions!C33 | F28: =-F11*Assumptions!C33 | G28: =-G11*Assumptions!C33 | H28: =-H11*Assumptions!C33 | I28: =-I11*Assumptions!C33 | J28: =-J11*Assumptions!C33 | K28: =-K11*Assumptions!C33 | L28: =-L11*Assumptions!C33 | M28: =-M11*Assumptions!C33
B29: Base | D29: =-D12*Assumptions!D33 | E29: =-E12*Assumptions!D33 | F29: =-F12*Assumptions!D33 | G29: =-G12*Assumptions!D33 | H29: =-H12*Assumptions!D33 | I29: =-I12*Assumptions!D33 | J29: =-J12*Assumptions!D33 | K29: =-K12*Assumptions!D33 | L29: =-L12*Assumptions!D33 | M29: =-M12*Assumptions!D33
B30: Bull | D30: =-D13*Assumptions!E33 | E30: =-E13*Assumptions!E33 | F30: =-F13*Assumptions!E33 | G30: =-G13*Assumptions!E33 | H30: =-H13*Assumptions!E33 | I30: =-I13*Assumptions!E33 | J30: =-J13*Assumptions!E33 | K30: =-K13*Assumptions!E33 | L30: =-L13*Assumptions!E33 | M30: =-M13*Assumptions!E33
A31: EBIT | B31: Bear | D31: =D25+D28 | E31: =E25+E28 | F31: =F25+F28 | G31: =G25+G28 | H31: =H25+H28 | I31: =I25+I28 | J31: =J25+J28 | K31: =K25+K28 | ... M31: =M25+M28
B32: Base | D32: =D26+D29 | E32: =E26+E29 | F32: =F26+F29 | G32: =G26+G29 | H32: =H26+H29 | I32: =I26+I29 | J32: =J26+J29 | K32: =K26+K29 | ... M32: =M26+M29
B33: Bull | D33: =D27+D30 | E33: =E27+E30 | F33: =F27+F30 | G33: =G27+G30 | H33: =H27+H30 | I33: =I27+I30 | J33: =J27+J30 | K33: =K27+K30 | ... M33: =M27+M30
A34: (−) Tax on EBIT | B34: Bear | D34: =-D31*Assumptions!C25 | E34: =-E31*Assumptions!C25 | F34: =-F31*Assumptions!C25 | G34: =-G31*Assumptions!C25 | H34: =-H31*Assumptions!C25 | I34: =-I31*Assumptions!C25 | J34: =-J31*Assumptions!C25 | K34: =-K31*Assumptions!C25 | L34: =-L31*Assumptions!C25 | M34: =-M31*Assumptions!C25
B35: Base | D35: =-D32*Assumptions!D25 | E35: =-E32*Assumptions!D25 | F35: =-F32*Assumptions!D25 | G35: =-G32*Assumptions!D25 | H35: =-H32*Assumptions!D25 | I35: =-I32*Assumptions!D25 | J35: =-J32*Assumptions!D25 | K35: =-K32*Assumptions!D25 | L35: =-L32*Assumptions!D25 | M35: =-M32*Assumptions!D25
B36: Bull | D36: =-D33*Assumptions!E25 | E36: =-E33*Assumptions!E25 | F36: =-F33*Assumptions!E25 | G36: =-G33*Assumptions!E25 | H36: =-H33*Assumptions!E25 | I36: =-I33*Assumptions!E25 | J36: =-J33*Assumptions!E25 | K36: =-K33*Assumptions!E25 | L36: =-L33*Assumptions!E25 | M36: =-M33*Assumptions!E25
A37: NOPAT | B37: Bear | D37: =D31+D34 | E37: =E31+E34 | F37: =F31+F34 | G37: =G31+G34 | H37: =H31+H34 | I37: =I31+I34 | J37: =J31+J34 | K37: =K31+K34 | ... M37: =M31+M34
B38: Base | D38: =D32+D35 | E38: =E32+E35 | F38: =F32+F35 | G38: =G32+G35 | H38: =H32+H35 | I38: =I32+I35 | J38: =J32+J35 | K38: =K32+K35 | ... M38: =M32+M35
B39: Bull | D39: =D33+D36 | E39: =E33+E36 | F39: =F33+F36 | G39: =G33+G36 | H39: =H33+H36 | I39: =I33+I36 | J39: =J33+J36 | K39: =K33+K36 | ... M39: =M33+M36
A40: (+) D&A | B40: Bear | D40: =-D28 | E40: =-E28 | F40: =-F28 | G40: =-G28 | H40: =-H28 | I40: =-I28 | J40: =-J28 | K40: =-K28 | ... M40: =-M28
B41: Base | D41: =-D29 | E41: =-E29 | F41: =-F29 | G41: =-G29 | H41: =-H29 | I41: =-I29 | J41: =-J29 | K41: =-K29 | ... M41: =-M29
B42: Bull | D42: =-D30 | E42: =-E30 | F42: =-F30 | G42: =-G30 | H42: =-H30 | I42: =-I30 | J42: =-J30 | K42: =-K30 | ... M42: =-M30
A43: (−) Capex | B43: Bear | D43: =-D11*Assumptions!C34 | E43: =-E11*Assumptions!C34 | F43: =-F11*Assumptions!C34 | G43: =-G11*Assumptions!C34 | H43: =-H11*Assumptions!C34 | I43: =-I11*Assumptions!C34 | J43: =-J11*Assumptions!C34 | K43: =-K11*Assumptions!C34 | L43: =-L11*Assumptions!C34 | M43: =-M11*Assumptions!C34
B44: Base | D44: =-D12*Assumptions!D34 | E44: =-E12*Assumptions!D34 | F44: =-F12*Assumptions!D34 | G44: =-G12*Assumptions!D34 | H44: =-H12*Assumptions!D34 | I44: =-I12*Assumptions!D34 | J44: =-J12*Assumptions!D34 | K44: =-K12*Assumptions!D34 | L44: =-L12*Assumptions!D34 | M44: =-M12*Assumptions!D34
B45: Bull | D45: =-D13*Assumptions!E34 | E45: =-E13*Assumptions!E34 | F45: =-F13*Assumptions!E34 | G45: =-G13*Assumptions!E34 | H45: =-H13*Assumptions!E34 | I45: =-I13*Assumptions!E34 | J45: =-J13*Assumptions!E34 | K45: =-K13*Assumptions!E34 | L45: =-L13*Assumptions!E34 | M45: =-M13*Assumptions!E34
A46: (−) ΔNWC | B46: Bear | D46: =-(D11-C11)*Assumptions!C35 | E46: =-(E11-D11)*Assumptions!C35 | F46: =-(F11-E11)*Assumptions!C35 | G46: =-(G11-F11)*Assumptions!C35 | H46: =-(H11-G11)*Assumptions!C35 | I46: =-(I11-H11)*Assumptions!C35 | J46: =-(J11-I11)*Assumptions!C35 | K46: =-(K11-J11)*Assumptions!C35 | L46: =-(L11-K11)*Assumptions!C35 | M46: =-(M11-L11)*Assumptions!C35
B47: Base | D47: =-(D12-C12)*Assumptions!D35 | E47: =-(E12-D12)*Assumptions!D35 | F47: =-(F12-E12)*Assumptions!D35 | G47: =-(G12-F12)*Assumptions!D35 | H47: =-(H12-G12)*Assumptions!D35 | I47: =-(I12-H12)*Assumptions!D35 | J47: =-(J12-I12)*Assumptions!D35 | K47: =-(K12-J12)*Assumptions!D35 | L47: =-(L12-K12)*Assumptions!D35 | M47: =-(M12-L12)*Assumptions!D35
B48: Bull | D48: =-(D13-C13)*Assumptions!E35 | E48: =-(E13-D13)*Assumptions!E35 | F48: =-(F13-E13)*Assumptions!E35 | G48: =-(G13-F13)*Assumptions!E35 | H48: =-(H13-G13)*Assumptions!E35 | I48: =-(I13-H13)*Assumptions!E35 | J48: =-(J13-I13)*Assumptions!E35 | K48: =-(K13-J13)*Assumptions!E35 | L48: =-(L13-K13)*Assumptions!E35 | M48: =-(M13-L13)*Assumptions!E35
A49: FCFF | B49: Bear | D49: =D37+D40+D43+D46 | E49: =E37+E40+E43+E46 | F49: =F37+F40+F43+F46 | G49: =G37+G40+G43+G46 | H49: =H37+H40+H43+H46 | I49: =I37+I40+I43+I46 | J49: =J37+J40+J43+J46 | K49: =K37+K40+K43+K46 | ... M49: =M37+M40+M43+M46
B50: Base | D50: =D38+D41+D44+D47 | E50: =E38+E41+E44+E47 | F50: =F38+F41+F44+F47 | G50: =G38+G41+G44+G47 | H50: =H38+H41+H44+H47 | I50: =I38+I41+I44+I47 | J50: =J38+J41+J44+J47 | K50: =K38+K41+K44+K47 | ... M50: =M38+M41+M44+M47
B51: Bull | D51: =D39+D42+D45+D48 | E51: =E39+E42+E45+E48 | F51: =F39+F42+F45+F48 | G51: =G39+G42+G45+G48 | H51: =H39+H42+H45+H48 | I51: =I39+I42+I45+I48 | J51: =J39+J42+J45+J48 | K51: =K39+K42+K45+K48 | ... M51: =M39+M42+M45+M48
A52: Discount factor @ WACC | B52: Bear | D52: =1/(1+Assumptions!C29)^D5 | E52: =1/(1+Assumptions!C29)^E5 | F52: =1/(1+Assumptions!C29)^F5 | G52: =1/(1+Assumptions!C29)^G5 | H52: =1/(1+Assumptions!C29)^H5 | I52: =1/(1+Assumptions!C29)^I5 | J52: =1/(1+Assumptions!C29)^J5 | K52: =1/(1+Assumptions!C29)^K5 | L52: =1/(1+Assumptions!C29)^L5 | M52: =1/(1+Assumptions!C29)^M5
B53: Base | D53: =1/(1+Assumptions!D29)^D5 | E53: =1/(1+Assumptions!D29)^E5 | F53: =1/(1+Assumptions!D29)^F5 | G53: =1/(1+Assumptions!D29)^G5 | H53: =1/(1+Assumptions!D29)^H5 | I53: =1/(1+Assumptions!D29)^I5 | J53: =1/(1+Assumptions!D29)^J5 | K53: =1/(1+Assumptions!D29)^K5 | L53: =1/(1+Assumptions!D29)^L5 | M53: =1/(1+Assumptions!D29)^M5
B54: Bull | D54: =1/(1+Assumptions!E29)^D5 | E54: =1/(1+Assumptions!E29)^E5 | F54: =1/(1+Assumptions!E29)^F5 | G54: =1/(1+Assumptions!E29)^G5 | H54: =1/(1+Assumptions!E29)^H5 | I54: =1/(1+Assumptions!E29)^I5 | J54: =1/(1+Assumptions!E29)^J5 | K54: =1/(1+Assumptions!E29)^K5 | L54: =1/(1+Assumptions!E29)^L5 | M54: =1/(1+Assumptions!E29)^M5
A55: PV of FCFF | B55: Bear | D55: =D49*D52 | E55: =E49*E52 | F55: =F49*F52 | G55: =G49*G52 | H55: =H49*H52 | I55: =I49*I52 | J55: =J49*J52 | K55: =K49*K52 | ... M55: =M49*M52
B56: Base | D56: =D50*D53 | E56: =E50*E53 | F56: =F50*F53 | G56: =G50*G53 | H56: =H50*H53 | I56: =I50*I53 | J56: =J50*J53 | K56: =K50*K53 | ... M56: =M50*M53
B57: Bull | D57: =D51*D54 | E57: =E51*E54 | F57: =F51*F54 | G57: =G51*G54 | H57: =H51*H54 | I57: =I51*I54 | J57: =J51*J54 | K57: =K51*K54 | ... M57: =M51*M54
A59: ④ WACC SUMMARY (linked from Assumptions)
A60: Driver | C60: Bear | D60: Base | E60: Bull
A61: Risk-free rate | C61: =Assumptions!C20 | D61: =Assumptions!D20 | E61: =Assumptions!E20
A62: Equity risk premium | C62: =Assumptions!C21 | D62: =Assumptions!D21 | E62: =Assumptions!E21
A63: Beta | C63: =Assumptions!C22 | D63: =Assumptions!D22 | E63: =Assumptions!E22
A64: Cost of equity (Ke) | C64: =Assumptions!C23 | D64: =Assumptions!D23 | E64: =Assumptions!E23
A65: After-tax cost of debt | C65: =Assumptions!C26 | D65: =Assumptions!D26 | E65: =Assumptions!E26
A66: Weight of equity | C66: =Assumptions!C27 | D66: =Assumptions!D27 | E66: =Assumptions!E27
A67: Weight of debt | C67: =Assumptions!C28 | D67: =Assumptions!D28 | E67: =Assumptions!E28
A68: WACC | C68: =Assumptions!C29 | D68: =Assumptions!D29 | E68: =Assumptions!E29
A70: ⑤ VALUATION SUMMARY (Bear / Base / Bull side by side)
A71: ₹ Crore unless stated | C71: Bear | D71: Base | E71: Bull
A72: Terminal-yr FCFF (FY36) | C72: =M49 | D72: =M50 | E72: =M51
A73: Terminal growth (g) | C73: =Assumptions!C36 | D73: =Assumptions!D36 | E73: =Assumptions!E36
A74: WACC | C74: =Assumptions!C29 | D74: =Assumptions!D29 | E74: =Assumptions!E29
A75: Terminal Value (GGM) | C75: =C72*(1+C73)/(C74-C73) | D75: =D72*(1+D73)/(D74-D73) | E75: =E72*(1+E73)/(E74-E73)
A76: PV of Terminal Value | C76: =C75/(1+C74)^M5 | D76: =D75/(1+D74)^M5 | E76: =E75/(1+E74)^M5
A77: PV of explicit FCFFs | C77: =SUM(D55:M55) | D77: =SUM(D56:M56) | E77: =SUM(D57:M57)
A78: Enterprise Value (EV) | C78: =C76+C77 | D78: =D76+D77 | E78: =E76+E77
A79: (+) Net Cash | C79: =Assumptions!B16 | D79: =Assumptions!B16 | E79: =Assumptions!B16
A80: Equity Value | C80: =C78+C79 | D80: =D78+D79 | E80: =E78+E79
A81: Diluted shares (Cr) | C81: =Assumptions!B8 | D81: =Assumptions!B8 | E81: =Assumptions!B8
A82: Implied value / share (₹) | C82: =C80/C81 | D82: =D80/D81 | E82: =E80/E81
A83: Current Market Price (₹) | C83: =Assumptions!B7 | D83: =Assumptions!B7 | E83: =Assumptions!B7
A84: Upside / (Downside) % | C84: =C82/C83-1 | D84: =D82/D83-1 | E84: =E82/E83-1
A85: PV(TV) as % of EV | C85: =C76/C78 | D85: =D76/D78 | E85: =E76/E78
A87: ⑥ SENSITIVITY — Implied Value/Share (₹): WACC (rows) × Terminal Growth (cols), Base case
A88: Base-case FCFF stream; GGM terminal value re-priced at each WACC × g.
B89: WACC \ g | C89: 0.045 | D89: 0.05 | E89: 0.055 | F89: 0.06 | G89: 0.065
B90: 0.128 | C90: =(SUMPRODUCT($D$50:$M$50,(1+$B90)^(-$D$5:$M$5))+($M$50*(1+C$89)/($B90-C$89))/(1+$B90)^10+Assumptions!B16)/Assumptions!B8 | D90: =(SUMPRODUCT($D$50:$M$50,(1+$B90)^(-$D$5:$M$5))+($M$50*(1+D$89)/($B90-D$89))/(1+$B90)^10+Assumptions!B16)/Assumptions!B8 | E90: =(SUMPRODUCT($D$50:$M$50,(1+$B90)^(-$D$5:$M$5))+($M$50*(1+E$89)/($B90-E$89))/(1+$B90)^10+Assumptions!B16)/Assumptions!B8 | F90: =(SUMPRODUCT($D$50:$M$50,(1+$B90)^(-$D$5:$M$5))+($M$50*(1+F$89)/($B90-F$89))/(1+$B90)^10+Assumptions!B16)/Assumptions!B8 | G90: =(SUMPRODUCT($D$50:$M$50,(1+$B90)^(-$D$5:$M$5))+($M$50*(1+G$89)/($B90-G$89))/(1+$B90)^10+Assumptions!B16)/Assumptions!B8
B91: 0.138 | C91: =(SUMPRODUCT($D$50:$M$50,(1+$B91)^(-$D$5:$M$5))+($M$50*(1+C$89)/($B91-C$89))/(1+$B91)^10+Assumptions!B16)/Assumptions!B8 | D91: =(SUMPRODUCT($D$50:$M$50,(1+$B91)^(-$D$5:$M$5))+($M$50*(1+D$89)/($B91-D$89))/(1+$B91)^10+Assumptions!B16)/Assumptions!B8 | E91: =(SUMPRODUCT($D$50:$M$50,(1+$B91)^(-$D$5:$M$5))+($M$50*(1+E$89)/($B91-E$89))/(1+$B91)^10+Assumptions!B16)/Assumptions!B8 | F91: =(SUMPRODUCT($D$50:$M$50,(1+$B91)^(-$D$5:$M$5))+($M$50*(1+F$89)/($B91-F$89))/(1+$B91)^10+Assumptions!B16)/Assumptions!B8 | G91: =(SUMPRODUCT($D$50:$M$50,(1+$B91)^(-$D$5:$M$5))+($M$50*(1+G$89)/($B91-G$89))/(1+$B91)^10+Assumptions!B16)/Assumptions!B8
B92: 0.148 | C92: =(SUMPRODUCT($D$50:$M$50,(1+$B92)^(-$D$5:$M$5))+($M$50*(1+C$89)/($B92-C$89))/(1+$B92)^10+Assumptions!B16)/Assumptions!B8 | D92: =(SUMPRODUCT($D$50:$M$50,(1+$B92)^(-$D$5:$M$5))+($M$50*(1+D$89)/($B92-D$89))/(1+$B92)^10+Assumptions!B16)/Assumptions!B8 | E92: =(SUMPRODUCT($D$50:$M$50,(1+$B92)^(-$D$5:$M$5))+($M$50*(1+E$89)/($B92-E$89))/(1+$B92)^10+Assumptions!B16)/Assumptions!B8 | F92: =(SUMPRODUCT($D$50:$M$50,(1+$B92)^(-$D$5:$M$5))+($M$50*(1+F$89)/($B92-F$89))/(1+$B92)^10+Assumptions!B16)/Assumptions!B8 | G92: =(SUMPRODUCT($D$50:$M$50,(1+$B92)^(-$D$5:$M$5))+($M$50*(1+G$89)/($B92-G$89))/(1+$B92)^10+Assumptions!B16)/Assumptions!B8
B93: 0.158 | C93: =(SUMPRODUCT($D$50:$M$50,(1+$B93)^(-$D$5:$M$5))+($M$50*(1+C$89)/($B93-C$89))/(1+$B93)^10+Assumptions!B16)/Assumptions!B8 | D93: =(SUMPRODUCT($D$50:$M$50,(1+$B93)^(-$D$5:$M$5))+($M$50*(1+D$89)/($B93-D$89))/(1+$B93)^10+Assumptions!B16)/Assumptions!B8 | E93: =(SUMPRODUCT($D$50:$M$50,(1+$B93)^(-$D$5:$M$5))+($M$50*(1+E$89)/($B93-E$89))/(1+$B93)^10+Assumptions!B16)/Assumptions!B8 | F93: =(SUMPRODUCT($D$50:$M$50,(1+$B93)^(-$D$5:$M$5))+($M$50*(1+F$89)/($B93-F$89))/(1+$B93)^10+Assumptions!B16)/Assumptions!B8 | G93: =(SUMPRODUCT($D$50:$M$50,(1+$B93)^(-$D$5:$M$5))+($M$50*(1+G$89)/($B93-G$89))/(1+$B93)^10+Assumptions!B16)/Assumptions!B8
B94: 0.168 | C94: =(SUMPRODUCT($D$50:$M$50,(1+$B94)^(-$D$5:$M$5))+($M$50*(1+C$89)/($B94-C$89))/(1+$B94)^10+Assumptions!B16)/Assumptions!B8 | D94: =(SUMPRODUCT($D$50:$M$50,(1+$B94)^(-$D$5:$M$5))+($M$50*(1+D$89)/($B94-D$89))/(1+$B94)^10+Assumptions!B16)/Assumptions!B8 | E94: =(SUMPRODUCT($D$50:$M$50,(1+$B94)^(-$D$5:$M$5))+($M$50*(1+E$89)/($B94-E$89))/(1+$B94)^10+Assumptions!B16)/Assumptions!B8 | F94: =(SUMPRODUCT($D$50:$M$50,(1+$B94)^(-$D$5:$M$5))+($M$50*(1+F$89)/($B94-F$89))/(1+$B94)^10+Assumptions!B16)/Assumptions!B8 | G94: =(SUMPRODUCT($D$50:$M$50,(1+$B94)^(-$D$5:$M$5))+($M$50*(1+G$89)/($B94-G$89))/(1+$B94)^10+Assumptions!B16)/Assumptions!B8
A97: ⑦ REVERSE DCF (what the market is pricing — Base WACC & g)
A98: Current Market Price (₹) | C98: =Assumptions!B7
A99: Diluted shares (Cr) | C99: =Assumptions!B8
A100: Market capitalisation | C100: =C98*C99
A101: (−) Net Cash | C101: =Assumptions!B16
A102: Implied Enterprise Value | C102: =C100-C101 | P102: Implied EV = Mkt-cap − Net Cash (Net Cash is negative ⇒ EV > mkt-cap).
A103: Base WACC | C103: =Assumptions!D29
A104: Base terminal growth (g) | C104: =Assumptions!D36
A105: Implied steady-state FCFF (yr-1) | C105: =C102*(C103-C104) | P105: Single-stage Gordon perpetuity: FCFF₁ that justifies today's EV.
A106: Model Base FY27 FCFF (explicit) | C106: =D50 | P106: For comparison vs the implied requirement.
A107: Model Base terminal FCFF (FY36) | C107: =M50
A108: Implied FCFF ÷ FY26 revenue | C108: =C105/Assumptions!B9 | P108: FCFF margin the market is pricing vs ~2–3% achievable for a jeweller.
A109: Assumed steady-state FCFF margin | C109: 0.04 | P109: Editable assumption (DCF sheet). ~4% is optimistic for gold retail.
...
